plotarchive/__init__.py
plotarchive/src/archive.py
plotarchive/src/__init__.py
plotarchive/src/__init__.cpython-310-x86_64-linux-gnu.so
plotarchive/src/test.py
plotarchive/src/archive.cpython-310-x86_64-linux-gnu.so
plotarchive/src/files.cpython-310-x86_64-linux-gnu.so
plotarchive/src/test.cpython-310-x86_64-linux-gnu.so
plotarchive/src/unarchive.cpython-310-x86_64-linux-gnu.so
plotarchive/src/files.py
plotarchive/src/unarchive.py
plotarchive-0.0.9.dist-info/RECORD
plotarchive-0.0.9.dist-info/METADATA
plotarchive-0.0.9.dist-info/LICENSE
plotarchive-0.0.9.dist-info/top_level.txt
plotarchive-0.0.9.dist-info/WHEEL
