Metadata-Version: 2.1
Name: plotarchive
Version: 0.0.9
Summary: An easy method to save code and data that generates scientific plots.
Home-page: https://github.com/buswinka/plotarchive
Author: Chris Buswinka
Author-email: buswinka@gmail.com
Classifier: Programming Language :: Python :: 3
Classifier: License :: OSI Approved :: MIT License
Classifier: Operating System :: OS Independent
Requires-Python: >=3.10
License-File: LICENSE
